Workbook

Sheet Supuestos
A1: Lloyd's Tavern · supuestos del modelo
A2: Celdas en azul con fondo amarillo = editables. Todo lo demás es fórmula. Lo observado sale del libro real (state/plan_lloyd y mesa original, 27–29/10/2026).
A4: CÓMO OPERA EL BOT
A5: Rotación diaria del capital (US$ operados / capital, por día) | B5: 0.6 | C5: Observado: mesa original ~1,0x/día (US$400 sobre US$100–230 en 2 días); libro 3,1x el día de la migración (atípico: rebalanceo). 0,6 es un régimen normal con posiciones de 12–48 h. Probá 0,3 y 1,0.
A6: Tamaño medio de cada operación (% del capital) | B6: 0.1 | C6: Observado: US$1.900 / 31 operaciones = US$61 sobre US$600 ≈ 10%.
A7: Días por mes | B7: 30 | C7: El bot opera todos los días.
A8: Rendimiento bruto mensual del libro (antes de nuestras comisiones) | B8: 0.1 | C8: Escenario base. Es LA incógnita: dos días de historial no alcanzan. Las hojas de escenarios lo varían de −10% a +40%.
A10: COSTOS DE EJECUCIÓN QUE PAGA EL CLIENTE (no son nuestros)
A11: Slippage medio por operación | B11: 0.021 | C11: Observado: 2,10% promedio en 19 operaciones con tokens. Ya está dentro del rendimiento bruto; se muestra para dimensionar.
A12: Comisión del pool/DEX por operación (Jupiter + LP) | B12: 0.003 | C12: Típico 0,25–0,30% en pools de Raydium/Meteora. Ya dentro del rendimiento bruto.
A14: PRICING ACTUAL
A15: Holders · comisión por operación (cada compra o venta) | B15: 0.01 | C15: Lo publicado hoy.
A16: Holders · comisión sobre ganancias | B16: 0 | C16: Lo publicado hoy: nada.
A17: Externos · comisión por operación | B17: 0.02 | C17: Lo publicado hoy.
A18: Externos · comisión sobre ganancias | B18: 0.1 | C18: Lo publicado hoy: 10% de cada operación ganadora. El modelo lo aplica sobre la ganancia neta mensual (con marca de agua), que es lo defendible.
A20: COSTOS NUESTROS · variables por operación
A21: Costo on-chain por operación (gas + prioridad), US$ | B21: 0.08 | C21: Solana: 0,0005–0,001 SOL con prioridad para confirmar rápido (≈ US$0,05–0,10 a SOL ≈ US$100). Lo paga la billetera del usuario, pero si queremos que no lo note lo absorbemos.
A22: Créditos RPC (Helius) por operación, US$ | B22: 0.01 | C22: Cada operación dispara cotización, simulación, envío y seguimiento. Con el plan Developer (10M créditos) sale ~US$0,005–0,02.
A24: COSTOS NUESTROS · fijos mensuales (US$)
A25: Servidores (Hetzner) | B25: 45 | C25: Estimado: el servidor del bot + el de la app. Ajustá con la factura real.
A26: Helius (RPC + webhooks) | B26: 49 | C26: Plan Developer. Pasa a US$249 (Business) a partir de ~50 usuarios activos por el volumen de llamadas; el modelo lo hace solo (ver Escenarios).
A27: Helius · umbral de usuarios para subir de plan | B27: 50 | C27: Supuesto. A partir de este número de usuarios se usa el plan Business.
A28: Helius · plan Business | B28: 249
A29: Claude (cerebro, sesiones de investigación, admin) | B29: 200 | C29: Hoy corre sobre la suscripción de Gastón. Poné acá la parte que le atribuís al bot.
A30: X/Twitter API (cazador de tweets) | B30: 0 | C30: Hoy apagado (el experimento se descartó). Si se reactiva: US$100–200/mes.
A31: Dominio, mail, varios | B31: 15
A33: USUARIOS
A34: Depósito promedio por usuario (US$) | B34: 1000 | C34: Tu pregunta: 10 personas con US$1.000 cada una.
A35: Proporción de usuarios que son holders de Nonco Genesis | B35: 0.5 | C35: Al principio, casi todos (entran primero). Con la lista de espera abierta, baja.
A37: DERIVADOS (fórmulas)
A38: Operaciones por día por usuario | B38: =Supuestos!$B$5/Supuestos!$B$6 -> 6 | C38: rotación / tamaño medio
A39: Operaciones por mes por usuario | B39: =B38*Supuestos!$B$7 -> 180
A40: Volumen operado por mes, como múltiplo del capital | B40: =Supuestos!$B$5*Supuestos!$B$7 -> 18 | C40: Con 0,6/día el bot opera 18 veces el capital por mes.
A41: Comisiones por operación que paga un HOLDER por mes (% de su capital) | B41: =B40*Supuestos!$B$15 -> 0.18 | C41: ← El número clave. Es lo que el bot tiene que ganar solo para que el cliente empate.
A42: Comisiones por operación que paga un EXTERNO por mes (% de su capital) | B42: =B40*Supuestos!$B$17 -> 0.36
A43: Costo on-chain + RPC por usuario por mes (US$) | B43: =B39*(Supuestos!$B$21+Supuestos!$B$22) -> 16.2

Sheet Escenarios
A1: Flujo mensual proyectado con el PRICING ACTUAL, por cantidad de usuarios
A2: Un mes. Depósito, mezcla holders/externos y rendimiento bruto vienen de Supuestos. Cambiá los usuarios en la fila 4 (azul).
A4: Usuarios | B4: 10 | C4: 25 | D4: 50 | E4: 100 | F4: 250 | G4: 1000
A5: Capital total en la plataforma (AUM) | B5: =B$4*Supuestos!$B$34 -> 10000 | C5: =C$4*Supuestos!$B$34 -> 25000 | D5: =D$4*Supuestos!$B$34 -> 50000 | E5: =E$4*Supuestos!$B$34 -> 100000 | F5: =F$4*Supuestos!$B$34 -> 250000 | G5: =G$4*Supuestos!$B$34 -> 1000000
A6: de holders | B6: =B5*Supuestos!$B$35 -> 5000 | C6: =C5*Supuestos!$B$35 -> 12500 | D6: =D5*Supuestos!$B$35 -> 25000 | E6: =E5*Supuestos!$B$35 -> 50000 | F6: =F5*Supuestos!$B$35 -> 125000 | G6: =G5*Supuestos!$B$35 -> 500000
A7: de externos | B7: =B5-B6 -> 5000 | C7: =C5-C6 -> 12500 | D7: =D5-D6 -> 25000 | E7: =E5-E6 -> 50000 | F7: =F5-F6 -> 125000 | G7: =G5-G6 -> 500000
A8: Operaciones por mes (todas las billeteras) | B8: =B$4*Supuestos!$B$39 -> 1800 | C8: =C$4*Supuestos!$B$39 -> 4500 | D8: =D$4*Supuestos!$B$39 -> 9000 | E8: =E$4*Supuestos!$B$39 -> 18000 | F8: =F$4*Supuestos!$B$39 -> 45000 | G8: =G$4*Supuestos!$B$39 -> 180000
A10: INGRESOS
A11: Comisión por operación · holders | B11: =B6*Supuestos!$B$41 -> 900 | C11: =C6*Supuestos!$B$41 -> 2250 | D11: =D6*Supuestos!$B$41 -> 4500 | E11: =E6*Supuestos!$B$41 -> 9000 | F11: =F6*Supuestos!$B$41 -> 22500 | G11: =G6*Supuestos!$B$41 -> 90000
A12: Comisión por operación · externos | B12: =B7*Supuestos!$B$42 -> 1800 | C12: =C7*Supuestos!$B$42 -> 4500 | D12: =D7*Supuestos!$B$42 -> 9000 | E12: =E7*Supuestos!$B$42 -> 18000 | F12: =F7*Supuestos!$B$42 -> 45000 | G12: =G7*Supuestos!$B$42 -> 180000
A13: Comisión sobre ganancias · externos | B13: =B7*MAX(0,Supuestos!$B$8-Supuestos!$B$42)*Supuestos!$B$18 -> 0 | C13: =C7*MAX(0,Supuestos!$B$8-Supuestos!$B$42)*Supuestos!$B$18 -> 0 | D13: =D7*MAX(0,Supuestos!$B$8-Supuestos!$B$42)*Supuestos!$B$18 -> 0 | E13: =E7*MAX(0,Supuestos!$B$8-Supuestos!$B$42)*Supuestos!$B$18 -> 0 | F13: =F7*MAX(0,Supuestos!$B$8-Supuestos!$B$42)*Supuestos!$B$18 -> 0 | G13: =G7*MAX(0,Supuestos!$B$8-Supuestos!$B$42)*Supuestos!$B$18 -> 0
A14: Comisión sobre ganancias · holders | B14: =B6*MAX(0,Supuestos!$B$8-Supuestos!$B$41)*Supuestos!$B$16 -> 0 | C14: =C6*MAX(0,Supuestos!$B$8-Supuestos!$B$41)*Supuestos!$B$16 -> 0 | D14: =D6*MAX(0,Supuestos!$B$8-Supuestos!$B$41)*Supuestos!$B$16 -> 0 | E14: =E6*MAX(0,Supuestos!$B$8-Supuestos!$B$41)*Supuestos!$B$16 -> 0 | F14: =F6*MAX(0,Supuestos!$B$8-Supuestos!$B$41)*Supuestos!$B$16 -> 0 | G14: =G6*MAX(0,Supuestos!$B$8-Supuestos!$B$41)*Supuestos!$B$16 -> 0
A15: Ingresos totales | B15: =SUM(B11:B14) -> 2700 | C15: =SUM(C11:C14) -> 6750 | D15: =SUM(D11:D14) -> 13500 | E15: =SUM(E11:E14) -> 27000 | F15: =SUM(F11:F14) -> 67500 | G15: =SUM(G11:G14) -> 270000
A17: COSTOS
A18: On-chain + RPC por operación | B18: =B$4*Supuestos!$B$43 -> 162 | C18: =C$4*Supuestos!$B$43 -> 405 | D18: =D$4*Supuestos!$B$43 -> 810 | E18: =E$4*Supuestos!$B$43 -> 1620 | F18: =F$4*Supuestos!$B$43 -> 4050 | G18: =G$4*Supuestos!$B$43 -> 16200
A19: Helius | B19: =IF(B$4>=Supuestos!$B$27,Supuestos!$B$28,Supuestos!$B$26) -> 49 | C19: =IF(C$4>=Supuestos!$B$27,Supuestos!$B$28,Supuestos!$B$26) -> 49 | D19: =IF(D$4>=Supuestos!$B$27,Supuestos!$B$28,Supuestos!$B$26) -> 249 | E19: =IF(E$4>=Supuestos!$B$27,Supuestos!$B$28,Supuestos!$B$26) -> 249 | F19: =IF(F$4>=Supuestos!$B$27,Supuestos!$B$28,Supuestos!$B$26) -> 249 | G19: =IF(G$4>=Supuestos!$B$27,Supuestos!$B$28,Supuestos!$B$26) -> 249
A20: Otros fijos (servidores, Claude, X, varios) | B20: =Supuestos!$B$25+Supuestos!$B$29+Supuestos!$B$30+Supuestos!$B$31 -> 260 | C20: =Supuestos!$B$25+Supuestos!$B$29+Supuestos!$B$30+Supuestos!$B$31 -> 260 | D20: =Supuestos!$B$25+Supuestos!$B$29+Supuestos!$B$30+Supuestos!$B$31 -> 260 | E20: =Supuestos!$B$25+Supuestos!$B$29+Supuestos!$B$30+Supuestos!$B$31 -> 260 | F20: =Supuestos!$B$25+Supuestos!$B$29+Supuestos!$B$30+Supuestos!$B$31 -> 260 | G20: =Supuestos!$B$25+Supuestos!$B$29+Supuestos!$B$30+Supuestos!$B$31 -> 260
A21: Costos totales | B21: =SUM(B18:B20) -> 471 | C21: =SUM(C18:C20) -> 714 | D21: =SUM(D18:D20) -> 1319 | E21: =SUM(E18:E20) -> 2129 | F21: =SUM(F18:F20) -> 4559 | G21: =SUM(G18:G20) -> 16709
A23: RESULTADO MENSUAL | B23: =B15-B21 -> 2229 | C23: =C15-C21 -> 6036 | D23: =D15-D21 -> 12181 | E23: =E15-E21 -> 24871 | F23: =F15-F21 -> 62941 | G23: =G15-G21 -> 253291
A24: Margen sobre ingresos | B24: =IF(B15=0,0,B23/B15) -> 0.82555556 | C24: =IF(C15=0,0,C23/C15) -> 0.89422222 | D24: =IF(D15=0,0,D23/D15) -> 0.9022963 | E24: =IF(E15=0,0,E23/E15) -> 0.92114815 | F24: =IF(F15=0,0,F23/F15) -> 0.93245926 | G24: =IF(G15=0,0,G23/G15) -> 0.93811481
A25: Ingreso por usuario por mes | B25: =IF(B$4=0,0,B15/B$4) -> 270 | C25: =IF(C$4=0,0,C15/C$4) -> 270 | D25: =IF(D$4=0,0,D15/D$4) -> 270 | E25: =IF(E$4=0,0,E15/E$4) -> 270 | F25: =IF(F$4=0,0,F15/F$4) -> 270 | G25: =IF(G$4=0,0,G15/G$4) -> 270
A27: LO QUE VE EL CLIENTE (externo)
A28: Rendimiento bruto del libro | B28: =Supuestos!$B$8 -> 0.1 | C28: =Supuestos!$B$8 -> 0.1 | D28: =Supuestos!$B$8 -> 0.1 | E28: =Supuestos!$B$8 -> 0.1 | F28: =Supuestos!$B$8 -> 0.1 | G28: =Supuestos!$B$8 -> 0.1
A29: − comisiones por operación | B29: =-Supuestos!$B$42 -> -0.36 | C29: =-Supuestos!$B$42 -> -0.36 | D29: =-Supuestos!$B$42 -> -0.36 | E29: =-Supuestos!$B$42 -> -0.36 | F29: =-Supuestos!$B$42 -> -0.36 | G29: =-Supuestos!$B$42 -> -0.36
A30: − comisión sobre ganancias | B30: =-MAX(0,Supuestos!$B$8-Supuestos!$B$42)*Supuestos!$B$18 -> 0 | C30: =-MAX(0,Supuestos!$B$8-Supuestos!$B$42)*Supuestos!$B$18 -> 0 | D30: =-MAX(0,Supuestos!$B$8-Supuestos!$B$42)*Supuestos!$B$18 -> 0 | E30: =-MAX(0,Supuestos!$B$8-Supuestos!$B$42)*Supuestos!$B$18 -> 0 | F30: =-MAX(0,Supuestos!$B$8-Supuestos!$B$42)*Supuestos!$B$18 -> 0 | G30: =-MAX(0,Supuestos!$B$8-Supuestos!$B$42)*Supuestos!$B$18 -> 0
A31: Rendimiento neto del cliente externo | B31: =B28+B29+B30 -> -0.26 | C31: =C28+C29+C30 -> -0.26 | D31: =D28+D29+D30 -> -0.26 | E31: =E28+E29+E30 -> -0.26 | F31: =F28+F29+F30 -> -0.26 | G31: =G28+G29+G30 -> -0.26
A32: Rendimiento neto del cliente holder | B32: =Supuestos!$B$8-Supuestos!$B$41-MAX(0,Supuestos!$B$8-Supuestos!$B$41)*Supuestos!$B$16 -> -0.08 | C32: =Supuestos!$B$8-Supuestos!$B$41-MAX(0,Supuestos!$B$8-Supuestos!$B$41)*Supuestos!$B$16 -> -0.08 | D32: =Supuestos!$B$8-Supuestos!$B$41-MAX(0,Supuestos!$B$8-Supuestos!$B$41)*Supuestos!$B$16 -> -0.08 | E32: =Supuestos!$B$8-Supuestos!$B$41-MAX(0,Supuestos!$B$8-Supuestos!$B$41)*Supuestos!$B$16 -> -0.08 | F32: =Supuestos!$B$8-Supuestos!$B$41-MAX(0,Supuestos!$B$8-Supuestos!$B$41)*Supuestos!$B$16 -> -0.08 | G32: =Supuestos!$B$8-Supuestos!$B$41-MAX(0,Supuestos!$B$8-Supuestos!$B$41)*Supuestos!$B$16 -> -0.08
A33: Rendimiento bruto que el bot necesita solo para que el externo empate | B33: =Supuestos!$B$42 -> 0.36 | C33: =Supuestos!$B$42 -> 0.36 | D33: =Supuestos!$B$42 -> 0.36 | E33: =Supuestos!$B$42 -> 0.36 | F33: =Supuestos!$B$42 -> 0.36 | G33: =Supuestos!$B$42 -> 0.36

Sheet Sensibilidad
A1: ¿Cuánto le queda al cliente con el pricing actual? Rendimiento neto mensual del cliente EXTERNO
A2: Filas: rendimiento bruto del libro en el mes. Columnas: rotación diaria del capital. Verde = el cliente gana; rojo = pierde aunque el bot haya ganado.
A4: bruto ↓ / rotación → | B4: 0.2 | C4: 0.4 | D4: 0.6 | E4: 0.8 | F4: 1 | G4: 1.5
A5: -0.1 | B5: =$A5-(B$4*Supuestos!$B$7*Supuestos!$B$17)-MAX(0,$A5-(B$4*Supuestos!$B$7*Supuestos!$B$17))*Supuestos!$B$18 -> -0.22 | C5: =$A5-(C$4*Supuestos!$B$7*Supuestos!$B$17)-MAX(0,$A5-(C$4*Supuestos!$B$7*Supuestos!$B$17))*Supuestos!$B$18 -> -0.34 | D5: =$A5-(D$4*Supuestos!$B$7*Supuestos!$B$17)-MAX(0,$A5-(D$4*Supuestos!$B$7*Supuestos!$B$17))*Supuestos!$B$18 -> -0.46 | E5: =$A5-(E$4*Supuestos!$B$7*Supuestos!$B$17)-MAX(0,$A5-(E$4*Supuestos!$B$7*Supuestos!$B$17))*Supuestos!$B$18 -> -0.58 | F5: =$A5-(F$4*Supuestos!$B$7*Supuestos!$B$17)-MAX(0,$A5-(F$4*Supuestos!$B$7*Supuestos!$B$17))*Supuestos!$B$18 -> -0.7 | G5: =$A5-(G$4*Supuestos!$B$7*Supuestos!$B$17)-MAX(0,$A5-(G$4*Supuestos!$B$7*Supuestos!$B$17))*Supuestos!$B$18 -> -1
A6: 0 | B6: =$A6-(B$4*Supuestos!$B$7*Supuestos!$B$17)-MAX(0,$A6-(B$4*Supuestos!$B$7*Supuestos!$B$17))*Supuestos!$B$18 -> -0.12 | C6: =$A6-(C$4*Supuestos!$B$7*Supuestos!$B$17)-MAX(0,$A6-(C$4*Supuestos!$B$7*Supuestos!$B$17))*Supuestos!$B$18 -> -0.24 | D6: =$A6-(D$4*Supuestos!$B$7*Supuestos!$B$17)-MAX(0,$A6-(D$4*Supuestos!$B$7*Supuestos!$B$17))*Supuestos!$B$18 -> -0.36 | E6: =$A6-(E$4*Supuestos!$B$7*Supuestos!$B$17)-MAX(0,$A6-(E$4*Supuestos!$B$7*Supuestos!$B$17))*Supuestos!$B$18 -> -0.48 | F6: =$A6-(F$4*Supuestos!$B$7*Supuestos!$B$17)-MAX(0,$A6-(F$4*Supuestos!$B$7*Supuestos!$B$17))*Supuestos!$B$18 -> -0.6 | G6: =$A6-(G$4*Supuestos!$B$7*Supuestos!$B$17)-MAX(0,$A6-(G$4*Supuestos!$B$7*Supuestos!$B$17))*Supuestos!$B$18 -> -0.9
A7: 0.05 | B7: =$A7-(B$4*Supuestos!$B$7*Supuestos!$B$17)-MAX(0,$A7-(B$4*Supuestos!$B$7*Supuestos!$B$17))*Supuestos!$B$18 -> -0.07 | C7: =$A7-(C$4*Supuestos!$B$7*Supuestos!$B$17)-MAX(0,$A7-(C$4*Supuestos!$B$7*Supuestos!$B$17))*Supuestos!$B$18 -> -0.19 | D7: =$A7-(D$4*Supuestos!$B$7*Supuestos!$B$17)-MAX(0,$A7-(D$4*Supuestos!$B$7*Supuestos!$B$17))*Supuestos!$B$18 -> -0.31 | E7: =$A7-(E$4*Supuestos!$B$7*Supuestos!$B$17)-MAX(0,$A7-(E$4*Supuestos!$B$7*Supuestos!$B$17))*Supuestos!$B$18 -> -0.43 | F7: =$A7-(F$4*Supuestos!$B$7*Supuestos!$B$17)-MAX(0,$A7-(F$4*Supuestos!$B$7*Supuestos!$B$17))*Supuestos!$B$18 -> -0.55 | G7: =$A7-(G$4*Supuestos!$B$7*Supuestos!$B$17)-MAX(0,$A7-(G$4*Supuestos!$B$7*Supuestos!$B$17))*Supuestos!$B$18 -> -0.85
A8: 0.1 | B8: =$A8-(B$4*Supuestos!$B$7*Supuestos!$B$17)-MAX(0,$A8-(B$4*Supuestos!$B$7*Supuestos!$B$17))*Supuestos!$B$18 -> -0.02 | C8: =$A8-(C$4*Supuestos!$B$7*Supuestos!$B$17)-MAX(0,$A8-(C$4*Supuestos!$B$7*Supuestos!$B$17))*Supuestos!$B$18 -> -0.14 | D8: =$A8-(D$4*Supuestos!$B$7*Supuestos!$B$17)-MAX(0,$A8-(D$4*Supuestos!$B$7*Supuestos!$B$17))*Supuestos!$B$18 -> -0.26 | E8: =$A8-(E$4*Supuestos!$B$7*Supuestos!$B$17)-MAX(0,$A8-(E$4*Supuestos!$B$7*Supuestos!$B$17))*Supuestos!$B$18 -> -0.38 | F8: =$A8-(F$4*Supuestos!$B$7*Supuestos!$B$17)-MAX(0,$A8-(F$4*Supuestos!$B$7*Supuestos!$B$17))*Supuestos!$B$18 -> -0.5 | G8: =$A8-(G$4*Supuestos!$B$7*Supuestos!$B$17)-MAX(0,$A8-(G$4*Supuestos!$B$7*Supuestos!$B$17))*Supuestos!$B$18 -> -0.8
A9: 0.2 | B9: =$A9-(B$4*Supuestos!$B$7*Supuestos!$B$17)-MAX(0,$A9-(B$4*Supuestos!$B$7*Supuestos!$B$17))*Supuestos!$B$18 -> 0.072 | C9: =$A9-(C$4*Supuestos!$B$7*Supuestos!$B$17)-MAX(0,$A9-(C$4*Supuestos!$B$7*Supuestos!$B$17))*Supuestos!$B$18 -> -0.04 | D9: =$A9-(D$4*Supuestos!$B$7*Supuestos!$B$17)-MAX(0,$A9-(D$4*Supuestos!$B$7*Supuestos!$B$17))*Supuestos!$B$18 -> -0.16 | E9: =$A9-(E$4*Supuestos!$B$7*Supuestos!$B$17)-MAX(0,$A9-(E$4*Supuestos!$B$7*Supuestos!$B$17))*Supuestos!$B$18 -> -0.28 | F9: =$A9-(F$4*Supuestos!$B$7*Supuestos!$B$17)-MAX(0,$A9-(F$4*Supuestos!$B$7*Supuestos!$B$17))*Supuestos!$B$18 -> -0.4 | G9: =$A9-(G$4*Supuestos!$B$7*Supuestos!$B$17)-MAX(0,$A9-(G$4*Supuestos!$B$7*Supuestos!$B$17))*Supuestos!$B$18 -> -0.7
A10: 0.3 | B10: =$A10-(B$4*Supuestos!$B$7*Supuestos!$B$17)-MAX(0,$A10-(B$4*Supuestos!$B$7*Supuestos!$B$17))*Supuestos!$B$18 -> 0.162 | C10: =$A10-(C$4*Supuestos!$B$7*Supuestos!$B$17)-MAX(0,$A10-(C$4*Supuestos!$B$7*Supuestos!$B$17))*Supuestos!$B$18 -> 0.054 | D10: =$A10-(D$4*Supuestos!$B$7*Supuestos!$B$17)-MAX(0,$A10-(D$4*Supuestos!$B$7*Supuestos!$B$17))*Supuestos!$B$18 -> -0.06 | E10: =$A10-(E$4*Supuestos!$B$7*Supuestos!$B$17)-MAX(0,$A10-(E$4*Supuestos!$B$7*Supuestos!$B$17))*Supuestos!$B$18 -> -0.18 | F10: =$A10-(F$4*Supuestos!$B$7*Supuestos!$B$17)-MAX(0,$A10-(F$4*Supuestos!$B$7*Supuestos!$B$17))*Supuestos!$B$18 -> -0.3 | G10: =$A10-(G$4*Supuestos!$B$7*Supuestos!$B$17)-MAX(0,$A10-(G$4*Supuestos!$B$7*Supuestos!$B$17))*Supuestos!$B$18 -> -0.6
A11: 0.5 | B11: =$A11-(B$4*Supuestos!$B$7*Supuestos!$B$17)-MAX(0,$A11-(B$4*Supuestos!$B$7*Supuestos!$B$17))*Supuestos!$B$18 -> 0.342 | C11: =$A11-(C$4*Supuestos!$B$7*Supuestos!$B$17)-MAX(0,$A11-(C$4*Supuestos!$B$7*Supuestos!$B$17))*Supuestos!$B$18 -> 0.234 | D11: =$A11-(D$4*Supuestos!$B$7*Supuestos!$B$17)-MAX(0,$A11-(D$4*Supuestos!$B$7*Supuestos!$B$17))*Supuestos!$B$18 -> 0.126 | E11: =$A11-(E$4*Supuestos!$B$7*Supuestos!$B$17)-MAX(0,$A11-(E$4*Supuestos!$B$7*Supuestos!$B$17))*Supuestos!$B$18 -> 0.018 | F11: =$A11-(F$4*Supuestos!$B$7*Supuestos!$B$17)-MAX(0,$A11-(F$4*Supuestos!$B$7*Supuestos!$B$17))*Supuestos!$B$18 -> -0.1 | G11: =$A11-(G$4*Supuestos!$B$7*Supuestos!$B$17)-MAX(0,$A11-(G$4*Supuestos!$B$7*Supuestos!$B$17))*Supuestos!$B$18 -> -0.4
A13: Misma tabla para un HOLDER (1% por operación, sin comisión sobre ganancias)
B14: =B$4 -> 0.2 | C14: =C$4 -> 0.4 | D14: =D$4 -> 0.6 | E14: =E$4 -> 0.8 | F14: =F$4 -> 1 | G14: =G$4 -> 1.5
A15: =$A5 -> -0.1 | B15: =$A15-(B$4*Supuestos!$B$7*Supuestos!$B$15)-MAX(0,$A15-(B$4*Supuestos!$B$7*Supuestos!$B$15))*Supuestos!$B$16 -> -0.16 | C15: =$A15-(C$4*Supuestos!$B$7*Supuestos!$B$15)-MAX(0,$A15-(C$4*Supuestos!$B$7*Supuestos!$B$15))*Supuestos!$B$16 -> -0.22 | D15: =$A15-(D$4*Supuestos!$B$7*Supuestos!$B$15)-MAX(0,$A15-(D$4*Supuestos!$B$7*Supuestos!$B$15))*Supuestos!$B$16 -> -0.28 | E15: =$A15-(E$4*Supuestos!$B$7*Supuestos!$B$15)-MAX(0,$A15-(E$4*Supuestos!$B$7*Supuestos!$B$15))*Supuestos!$B$16 -> -0.34 | F15: =$A15-(F$4*Supuestos!$B$7*Supuestos!$B$15)-MAX(0,$A15-(F$4*Supuestos!$B$7*Supuestos!$B$15))*Supuestos!$B$16 -> -0.4 | G15: =$A15-(G$4*Supuestos!$B$7*Supuestos!$B$15)-MAX(0,$A15-(G$4*Supuestos!$B$7*Supuestos!$B$15))*Supuestos!$B$16 -> -0.55
A16: =$A6 -> 0 | B16: =$A16-(B$4*Supuestos!$B$7*Supuestos!$B$15)-MAX(0,$A16-(B$4*Supuestos!$B$7*Supuestos!$B$15))*Supuestos!$B$16 -> -0.06 | C16: =$A16-(C$4*Supuestos!$B$7*Supuestos!$B$15)-MAX(0,$A16-(C$4*Supuestos!$B$7*Supuestos!$B$15))*Supuestos!$B$16 -> -0.12 | D16: =$A16-(D$4*Supuestos!$B$7*Supuestos!$B$15)-MAX(0,$A16-(D$4*Supuestos!$B$7*Supuestos!$B$15))*Supuestos!$B$16 -> -0.18 | E16: =$A16-(E$4*Supuestos!$B$7*Supuestos!$B$15)-MAX(0,$A16-(E$4*Supuestos!$B$7*Supuestos!$B$15))*Supuestos!$B$16 -> -0.24 | F16: =$A16-(F$4*Supuestos!$B$7*Supuestos!$B$15)-MAX(0,$A16-(F$4*Supuestos!$B$7*Supuestos!$B$15))*Supuestos!$B$16 -> -0.3 | G16: =$A16-(G$4*Supuestos!$B$7*Supuestos!$B$15)-MAX(0,$A16-(G$4*Supuestos!$B$7*Supuestos!$B$15))*Supuestos!$B$16 -> -0.45
A17: =$A7 -> 0.05 | B17: =$A17-(B$4*Supuestos!$B$7*Supuestos!$B$15)-MAX(0,$A17-(B$4*Supuestos!$B$7*Supuestos!$B$15))*Supuestos!$B$16 -> -0.01 | C17: =$A17-(C$4*Supuestos!$B$7*Supuestos!$B$15)-MAX(0,$A17-(C$4*Supuestos!$B$7*Supuestos!$B$15))*Supuestos!$B$16 -> -0.07 | D17: =$A17-(D$4*Supuestos!$B$7*Supuestos!$B$15)-MAX(0,$A17-(D$4*Supuestos!$B$7*Supuestos!$B$15))*Supuestos!$B$16 -> -0.13 | E17: =$A17-(E$4*Supuestos!$B$7*Supuestos!$B$15)-MAX(0,$A17-(E$4*Supuestos!$B$7*Supuestos!$B$15))*Supuestos!$B$16 -> -0.19 | F17: =$A17-(F$4*Supuestos!$B$7*Supuestos!$B$15)-MAX(0,$A17-(F$4*Supuestos!$B$7*Supuestos!$B$15))*Supuestos!$B$16 -> -0.25 | G17: =$A17-(G$4*Supuestos!$B$7*Supuestos!$B$15)-MAX(0,$A17-(G$4*Supuestos!$B$7*Supuestos!$B$15))*Supuestos!$B$16 -> -0.4
A18: =$A8 -> 0.1 | B18: =$A18-(B$4*Supuestos!$B$7*Supuestos!$B$15)-MAX(0,$A18-(B$4*Supuestos!$B$7*Supuestos!$B$15))*Supuestos!$B$16 -> 0.04 | C18: =$A18-(C$4*Supuestos!$B$7*Supuestos!$B$15)-MAX(0,$A18-(C$4*Supuestos!$B$7*Supuestos!$B$15))*Supuestos!$B$16 -> -0.02 | D18: =$A18-(D$4*Supuestos!$B$7*Supuestos!$B$15)-MAX(0,$A18-(D$4*Supuestos!$B$7*Supuestos!$B$15))*Supuestos!$B$16 -> -0.08 | E18: =$A18-(E$4*Supuestos!$B$7*Supuestos!$B$15)-MAX(0,$A18-(E$4*Supuestos!$B$7*Supuestos!$B$15))*Supuestos!$B$16 -> -0.14 | F18: =$A18-(F$4*Supuestos!$B$7*Supuestos!$B$15)-MAX(0,$A18-(F$4*Supuestos!$B$7*Supuestos!$B$15))*Supuestos!$B$16 -> -0.2 | G18: =$A18-(G$4*Supuestos!$B$7*Supuestos!$B$15)-MAX(0,$A18-(G$4*Supuestos!$B$7*Supuestos!$B$15))*Supuestos!$B$16 -> -0.35
A19: =$A9 -> 0.2 | B19: =$A19-(B$4*Supuestos!$B$7*Supuestos!$B$15)-MAX(0,$A19-(B$4*Supuestos!$B$7*Supuestos!$B$15))*Supuestos!$B$16 -> 0.14 | C19: =$A19-(C$4*Supuestos!$B$7*Supuestos!$B$15)-MAX(0,$A19-(C$4*Supuestos!$B$7*Supuestos!$B$15))*Supuestos!$B$16 -> 0.08 | D19: =$A19-(D$4*Supuestos!$B$7*Supuestos!$B$15)-MAX(0,$A19-(D$4*Supuestos!$B$7*Supuestos!$B$15))*Supuestos!$B$16 -> 0.02 | E19: =$A19-(E$4*Supuestos!$B$7*Supuestos!$B$15)-MAX(0,$A19-(E$4*Supuestos!$B$7*Supuestos!$B$15))*Supuestos!$B$16 -> -0.04 | F19: =$A19-(F$4*Supuestos!$B$7*Supuestos!$B$15)-MAX(0,$A19-(F$4*Supuestos!$B$7*Supuestos!$B$15))*Supuestos!$B$16 -> -0.1 | G19: =$A19-(G$4*Supuestos!$B$7*Supuestos!$B$15)-MAX(0,$A19-(G$4*Supuestos!$B$7*Supuestos!$B$15))*Supuestos!$B$16 -> -0.25
A20: =$A10 -> 0.3 | B20: =$A20-(B$4*Supuestos!$B$7*Supuestos!$B$15)-MAX(0,$A20-(B$4*Supuestos!$B$7*Supuestos!$B$15))*Supuestos!$B$16 -> 0.24 | C20: =$A20-(C$4*Supuestos!$B$7*Supuestos!$B$15)-MAX(0,$A20-(C$4*Supuestos!$B$7*Supuestos!$B$15))*Supuestos!$B$16 -> 0.18 | D20: =$A20-(D$4*Supuestos!$B$7*Supuestos!$B$15)-MAX(0,$A20-(D$4*Supuestos!$B$7*Supuestos!$B$15))*Supuestos!$B$16 -> 0.12 | E20: =$A20-(E$4*Supuestos!$B$7*Supuestos!$B$15)-MAX(0,$A20-(E$4*Supuestos!$B$7*Supuestos!$B$15))*Supuestos!$B$16 -> 0.06 | F20: =$A20-(F$4*Supuestos!$B$7*Supuestos!$B$15)-MAX(0,$A20-(F$4*Supuestos!$B$7*Supuestos!$B$15))*Supuestos!$B$16 -> 0 | G20: =$A20-(G$4*Supuestos!$B$7*Supuestos!$B$15)-MAX(0,$A20-(G$4*Supuestos!$B$7*Supuestos!$B$15))*Supuestos!$B$16 -> -0.15
A21: =$A11 -> 0.5 | B21: =$A21-(B$4*Supuestos!$B$7*Supuestos!$B$15)-MAX(0,$A21-(B$4*Supuestos!$B$7*Supuestos!$B$15))*Supuestos!$B$16 -> 0.44 | C21: =$A21-(C$4*Supuestos!$B$7*Supuestos!$B$15)-MAX(0,$A21-(C$4*Supuestos!$B$7*Supuestos!$B$15))*Supuestos!$B$16 -> 0.38 | D21: =$A21-(D$4*Supuestos!$B$7*Supuestos!$B$15)-MAX(0,$A21-(D$4*Supuestos!$B$7*Supuestos!$B$15))*Supuestos!$B$16 -> 0.32 | E21: =$A21-(E$4*Supuestos!$B$7*Supuestos!$B$15)-MAX(0,$A21-(E$4*Supuestos!$B$7*Supuestos!$B$15))*Supuestos!$B$16 -> 0.26 | F21: =$A21-(F$4*Supuestos!$B$7*Supuestos!$B$15)-MAX(0,$A21-(F$4*Supuestos!$B$7*Supuestos!$B$15))*Supuestos!$B$16 -> 0.2 | G21: =$A21-(G$4*Supuestos!$B$7*Supuestos!$B$15)-MAX(0,$A21-(G$4*Supuestos!$B$7*Supuestos!$B$15))*Supuestos!$B$16 -> 0.05

Sheet Alternativas
A1: Tres formas de cobrar, comparadas con los mismos supuestos
A2: Editá los azules. Cada columna es un modelo de pricing; abajo, qué le queda al cliente y qué nos queda a nosotros por cada US$1.000 de un cliente externo, en un mes.
B4: A · Actual | C4: B · Mixto | D4: C · Solo éxito
A5: Externos · comisión por operación | B5: =Supuestos!$B$17 -> 0.02 | C5: 0.0025 | D5: 0
A6: Externos · comisión sobre ganancia neta mensual (con marca de agua) | B6: =Supuestos!$B$18 -> 0.1 | C6: 0.2 | D6: 0.25
A7: Holders · comisión por operación | B7: =Supuestos!$B$15 -> 0.01 | C7: 0.0025 | D7: 0
A8: Holders · comisión sobre ganancia neta mensual | B8: =Supuestos!$B$16 -> 0 | C8: 0.1 | D8: 0.15
A9: Cuota fija mensual por usuario (US$) | B9: 0 | C9: 0 | D9: 0
A10: Nota: B y C cobran sobre la ganancia NETA del mes y solo por encima del máximo anterior (marca de agua). Es el estándar de fondos y copy-trading; nadie paga por recuperar lo que perdió.
A12: POR CADA US$1.000 DE UN CLIENTE EXTERNO, EN UN MES
A13: Ganancia bruta del libro (US$) | B13: =1000*Supuestos!$B$8 -> 100 | C13: =1000*Supuestos!$B$8 -> 100 | D13: =1000*Supuestos!$B$8 -> 100
A14: Comisiones por operación (US$) | B14: =1000*Supuestos!$B$40*B$5 -> 360 | C14: =1000*Supuestos!$B$40*C$5 -> 45 | D14: =1000*Supuestos!$B$40*D$5 -> 0
A15: Ganancia neta antes de la comisión de éxito (US$) | B15: =B13-B14 -> -260 | C15: =C13-C14 -> 55 | D15: =D13-D14 -> 100
A16: Comisión de éxito (US$) | B16: =MAX(0,B15)*B$6 -> 0 | C16: =MAX(0,C15)*C$6 -> 11 | D16: =MAX(0,D15)*D$6 -> 25
A17: Cuota fija (US$) | B17: =B$9 -> 0 | C17: =C$9 -> 0 | D17: =D$9 -> 0
A18: Al cliente le queda (US$) | B18: =B15-B16-B17 -> -260 | C18: =C15-C16-C17 -> 44 | D18: =D15-D16-D17 -> 75
A19: Rendimiento neto del cliente | B19: =B18/1000 -> -0.26 | C19: =C18/1000 -> 0.044 | D19: =D18/1000 -> 0.075
A20: Nos queda (US$) | B20: =B14+B16+B17 -> 360 | C20: =C14+C16+C17 -> 56 | D20: =D14+D16+D17 -> 25
A21: Costo nuestro on-chain + RPC (US$) | B21: =Supuestos!$B$43 -> 16.2 | C21: =Supuestos!$B$43 -> 16.2 | D21: =Supuestos!$B$43 -> 16.2
A22: Margen bruto nuestro por cliente (US$) | B22: =B20-B21 -> 343.8 | C22: =C20-C21 -> 39.8 | D22: =D20-D21 -> 8.8
A23: Bruto que el bot necesita para que el cliente empate | B23: =B14/1000 -> 0.36 | C23: =C14/1000 -> 0.045 | D23: =D14/1000 -> 0
A25: LOS MISMOS TRES MODELOS EN UN MES MALO (bruto −10%)
A26: Ganancia bruta del libro (US$) | B26: =1000*-0.1 -> -100 | C26: =1000*-0.1 -> -100 | D26: =1000*-0.1 -> -100
A27: Comisiones por operación (US$) | B27: =1000*Supuestos!$B$40*B$5 -> 360 | C27: =1000*Supuestos!$B$40*C$5 -> 45 | D27: =1000*Supuestos!$B$40*D$5 -> 0
A28: Al cliente le queda (US$) | B28: =B26-B27-B$9 -> -460 | C28: =C26-C27-C$9 -> -145 | D28: =D26-D27-D$9 -> -100
A29: Nos queda (US$) | B29: =B27+B$9 -> 360 | C29: =C27+C$9 -> 45 | D29: =D27+D$9 -> 0
A31: Lectura: en A cobramos lo mismo gane o pierda el cliente (y más cuanto más opera el bot, que es un incentivo peligroso). En B y C cobramos cuando el cliente gana; en el mes malo cobramos poco o nada, que es lo que hace que la gente se quede.

Sheet Escenarios B
A1: Flujo mensual proyectado con el PRICING B (mixto), por cantidad de usuarios
A2: Mismos supuestos que Escenarios; comisiones tomadas de la columna B de Alternativas.
A4: Usuarios | B4: =Escenarios!B4 -> 10 | C4: =Escenarios!C4 -> 25 | D4: =Escenarios!D4 -> 50 | E4: =Escenarios!E4 -> 100 | F4: =Escenarios!F4 -> 250 | G4: =Escenarios!G4 -> 1000
A5: Capital total en la plataforma (AUM) | B5: =B$4*Supuestos!$B$34 -> 10000 | C5: =C$4*Supuestos!$B$34 -> 25000 | D5: =D$4*Supuestos!$B$34 -> 50000 | E5: =E$4*Supuestos!$B$34 -> 100000 | F5: =F$4*Supuestos!$B$34 -> 250000 | G5: =G$4*Supuestos!$B$34 -> 1000000
A6: de holders | B6: =B5*Supuestos!$B$35 -> 5000 | C6: =C5*Supuestos!$B$35 -> 12500 | D6: =D5*Supuestos!$B$35 -> 25000 | E6: =E5*Supuestos!$B$35 -> 50000 | F6: =F5*Supuestos!$B$35 -> 125000 | G6: =G5*Supuestos!$B$35 -> 500000
A7: de externos | B7: =B5-B6 -> 5000 | C7: =C5-C6 -> 12500 | D7: =D5-D6 -> 25000 | E7: =E5-E6 -> 50000 | F7: =F5-F6 -> 125000 | G7: =G5-G6 -> 500000
A8: Ingresos · comisión por operación | B8: =(B6*Alternativas!$C$7+B7*Alternativas!$C$5)*Supuestos!$B$40 -> 450 | C8: =(C6*Alternativas!$C$7+C7*Alternativas!$C$5)*Supuestos!$B$40 -> 1125 | D8: =(D6*Alternativas!$C$7+D7*Alternativas!$C$5)*Supuestos!$B$40 -> 2250 | E8: =(E6*Alternativas!$C$7+E7*Alternativas!$C$5)*Supuestos!$B$40 -> 4500 | F8: =(F6*Alternativas!$C$7+F7*Alternativas!$C$5)*Supuestos!$B$40 -> 11250 | G8: =(G6*Alternativas!$C$7+G7*Alternativas!$C$5)*Supuestos!$B$40 -> 45000
A9: Ingresos · comisión de éxito | B9: =B7*MAX(0,Supuestos!$B$8-Supuestos!$B$40*Alternativas!$C$5)*Alternativas!$C$6+B6*MAX(0,Supuestos!$B$8-Supuestos!$B$40*Alternativas!$C$7)*Alternativas!$C$8 -> 82.5 | C9: =C7*MAX(0,Supuestos!$B$8-Supuestos!$B$40*Alternativas!$C$5)*Alternativas!$C$6+C6*MAX(0,Supuestos!$B$8-Supuestos!$B$40*Alternativas!$C$7)*Alternativas!$C$8 -> 206.25 | D9: =D7*MAX(0,Supuestos!$B$8-Supuestos!$B$40*Alternativas!$C$5)*Alternativas!$C$6+D6*MAX(0,Supuestos!$B$8-Supuestos!$B$40*Alternativas!$C$7)*Alternativas!$C$8 -> 412.5 | E9: =E7*MAX(0,Supuestos!$B$8-Supuestos!$B$40*Alternativas!$C$5)*Alternativas!$C$6+E6*MAX(0,Supuestos!$B$8-Supuestos!$B$40*Alternativas!$C$7)*Alternativas!$C$8 -> 825 | F9: =F7*MAX(0,Supuestos!$B$8-Supuestos!$B$40*Alternativas!$C$5)*Alternativas!$C$6+F6*MAX(0,Supuestos!$B$8-Supuestos!$B$40*Alternativas!$C$7)*Alternativas!$C$8 -> 2062.5 | G9: =G7*MAX(0,Supuestos!$B$8-Supuestos!$B$40*Alternativas!$C$5)*Alternativas!$C$6+G6*MAX(0,Supuestos!$B$8-Supuestos!$B$40*Alternativas!$C$7)*Alternativas!$C$8 -> 8250
A10: Ingresos · cuota fija | B10: =B$4*Alternativas!$C$9 -> 0 | C10: =C$4*Alternativas!$C$9 -> 0 | D10: =D$4*Alternativas!$C$9 -> 0 | E10: =E$4*Alternativas!$C$9 -> 0 | F10: =F$4*Alternativas!$C$9 -> 0 | G10: =G$4*Alternativas!$C$9 -> 0
A11: Ingresos totales | B11: =SUM(B8:B10) -> 532.5 | C11: =SUM(C8:C10) -> 1331.25 | D11: =SUM(D8:D10) -> 2662.5 | E11: =SUM(E8:E10) -> 5325 | F11: =SUM(F8:F10) -> 13312.5 | G11: =SUM(G8:G10) -> 53250
A12: Costos totales | B12: =Escenarios!B21 -> 471 | C12: =Escenarios!C21 -> 714 | D12: =Escenarios!D21 -> 1319 | E12: =Escenarios!E21 -> 2129 | F12: =Escenarios!F21 -> 4559 | G12: =Escenarios!G21 -> 16709
A13: RESULTADO MENSUAL | B13: =B11-B12 -> 61.5 | C13: =C11-C12 -> 617.25 | D13: =D11-D12 -> 1343.5 | E13: =E11-E12 -> 3196 | F13: =F11-F12 -> 8753.5 | G13: =G11-G12 -> 36541
A14: Rendimiento neto del cliente externo | B14: =Supuestos!$B$8-Supuestos!$B$40*Alternativas!$C$5-MAX(0,Supuestos!$B$8-Supuestos!$B$40*Alternativas!$C$5)*Alternativas!$C$6 -> 0.044 | C14: =Supuestos!$B$8-Supuestos!$B$40*Alternativas!$C$5-MAX(0,Supuestos!$B$8-Supuestos!$B$40*Alternativas!$C$5)*Alternativas!$C$6 -> 0.044 | D14: =Supuestos!$B$8-Supuestos!$B$40*Alternativas!$C$5-MAX(0,Supuestos!$B$8-Supuestos!$B$40*Alternativas!$C$5)*Alternativas!$C$6 -> 0.044 | E14: =Supuestos!$B$8-Supuestos!$B$40*Alternativas!$C$5-MAX(0,Supuestos!$B$8-Supuestos!$B$40*Alternativas!$C$5)*Alternativas!$C$6 -> 0.044 | F14: =Supuestos!$B$8-Supuestos!$B$40*Alternativas!$C$5-MAX(0,Supuestos!$B$8-Supuestos!$B$40*Alternativas!$C$5)*Alternativas!$C$6 -> 0.044 | G14: =Supuestos!$B$8-Supuestos!$B$40*Alternativas!$C$5-MAX(0,Supuestos!$B$8-Supuestos!$B$40*Alternativas!$C$5)*Alternativas!$C$6 -> 0.044
A15: Rendimiento neto del cliente holder | B15: =Supuestos!$B$8-Supuestos!$B$40*Alternativas!$C$7-MAX(0,Supuestos!$B$8-Supuestos!$B$40*Alternativas!$C$7)*Alternativas!$C$8 -> 0.0495 | C15: =Supuestos!$B$8-Supuestos!$B$40*Alternativas!$C$7-MAX(0,Supuestos!$B$8-Supuestos!$B$40*Alternativas!$C$7)*Alternativas!$C$8 -> 0.0495 | D15: =Supuestos!$B$8-Supuestos!$B$40*Alternativas!$C$7-MAX(0,Supuestos!$B$8-Supuestos!$B$40*Alternativas!$C$7)*Alternativas!$C$8 -> 0.0495 | E15: =Supuestos!$B$8-Supuestos!$B$40*Alternativas!$C$7-MAX(0,Supuestos!$B$8-Supuestos!$B$40*Alternativas!$C$7)*Alternativas!$C$8 -> 0.0495 | F15: =Supuestos!$B$8-Supuestos!$B$40*Alternativas!$C$7-MAX(0,Supuestos!$B$8-Supuestos!$B$40*Alternativas!$C$7)*Alternativas!$C$8 -> 0.0495 | G15: =Supuestos!$B$8-Supuestos!$B$40*Alternativas!$C$7-MAX(0,Supuestos!$B$8-Supuestos!$B$40*Alternativas!$C$7)*Alternativas!$C$8 -> 0.0495
